{
  "step1": {
    "completed_at": "2026-03-14T08:52:49.701932+00:00",
    "validation_status": "PASS"
  },
  "started_at": "2026-03-14T08:52:49.701936+00:00",
  "step2": {
    "completed_at": "2026-03-14T08:54:31.005411+00:00",
    "validation_status": "PASS"
  },
  "step3b": {
    "completed_at": "2026-03-14T10:56:37.972969+00:00",
    "validation_status": "PASS"
  },
  "step3c": {
    "completed_at": "2026-03-14T17:47:00.350507+00:00",
    "validation_status": "PASS"
  },
  "step4": {
    "completed_at": "2026-03-15T09:00:02.589419+00:00",
    "validation_status": "PASS"
  },
  "step3": {
    "completed_at": "2026-03-15T09:08:48.919774+00:00",
    "validation_status": "PASS"
  }
}